README.md
setup.cfg
setup.py
TOPSIS_AnshGupta_101803121/__init__.py
TOPSIS_Ansh_Gupta_101803121.egg-info/PKG-INFO
TOPSIS_Ansh_Gupta_101803121.egg-info/SOURCES.txt
TOPSIS_Ansh_Gupta_101803121.egg-info/dependency_links.txt
TOPSIS_Ansh_Gupta_101803121.egg-info/requires.txt
TOPSIS_Ansh_Gupta_101803121.egg-info/top_level.txt