Metadata-Version: 2.1
Name: TOPSIS-Ansh-Gupta-101803121
Version: 0.0.4
Summary: Implementation of TOPSIS
Home-page: https://github.com/PROFESSORRQ/TOPSIS_AnshGupta
Author: Ansh Gupta
Author-email: agupta2_be18@thapar.edu
License: UNKNOWN
Keywords: topsis pandas rank
Platform: UNKNOWN
Classifier: Programming Language :: Python :: 3
Classifier: License :: OSI Approved :: MIT License
Classifier: Operating System :: OS Independent
Requires-Python: >=3.0
